allcaptcha/__init__.py
allcaptcha/apps.py
allcaptcha/mixins.py
allcaptcha/settings.py
allcaptcha/utils.py
allcaptcha/migrations/__init__.py
allcaptcha/static/allcaptcha/allcaptcha.min.js
allcaptcha/templates/allcaptcha/challenge.html
allcaptcha/templatetags/__init__.py
allcaptcha/templatetags/allcaptcha_tags.py
allcaptcha/tests/__init__.py
allcaptcha/tests/test_mixins.py
allcaptcha/tests/test_templatetags.py
allcaptcha/tests/test_utils.py
allcaptcha/tests/utils.py
django_allcaptcha-0.3.0.dist-info/LICENSE
django_allcaptcha-0.3.0.dist-info/METADATA
django_allcaptcha-0.3.0.dist-info/WHEEL
django_allcaptcha-0.3.0.dist-info/top_level.txt
django_allcaptcha-0.3.0.dist-info/RECORD
